nonebot_plugin_web/__init__.py
nonebot_plugin_web/dist/favicon.ico
nonebot_plugin_web/dist/favicon.ico.bak
nonebot_plugin_web/dist/img/icons/android-chrome-192x192.png
nonebot_plugin_web/dist/img/icons/android-chrome-512x512.png
nonebot_plugin_web/dist/img/icons/android-chrome-maskable-192x192.png
nonebot_plugin_web/dist/img/icons/android-chrome-maskable-512x512.png
nonebot_plugin_web/dist/img/icons/apple-touch-icon-120x120.png
nonebot_plugin_web/dist/img/icons/apple-touch-icon-152x152.png
nonebot_plugin_web/dist/img/icons/apple-touch-icon-180x180.png
nonebot_plugin_web/dist/img/icons/apple-touch-icon-60x60.png
nonebot_plugin_web/dist/img/icons/apple-touch-icon-76x76.png
nonebot_plugin_web/dist/img/icons/apple-touch-icon.png
nonebot_plugin_web/dist/img/icons/favicon-16x16.png
nonebot_plugin_web/dist/img/icons/favicon-32x32.png
nonebot_plugin_web/dist/img/icons/msapplication-icon-144x144.png
nonebot_plugin_web/dist/img/icons/mstile-150x150.png
nonebot_plugin_web/dist/img/icons/safari-pinned-tab.svg
nonebot_plugin_web/dist/index.html
nonebot_plugin_web/dist/manifest.json
nonebot_plugin_web/dist/precache-manifest.63af17d3dc2ddc9792f1506dffcf27d5.js
nonebot_plugin_web/dist/robots.txt
nonebot_plugin_web/dist/service-worker.js
nonebot_plugin_web/dist/static/css/app.424d2b52.css
nonebot_plugin_web/dist/static/css/chunk-vendors.dc80cc34.css
nonebot_plugin_web/dist/static/fonts/element-icons.535877f5.woff
nonebot_plugin_web/dist/static/fonts/element-icons.732389de.ttf
nonebot_plugin_web/dist/static/js/app.28fec41e.js
nonebot_plugin_web/dist/static/js/app.28fec41e.js.map
nonebot_plugin_web/dist/static/js/chunk-vendors.25940a71.js
nonebot_plugin_web/dist/static/js/chunk-vendors.25940a71.js.map
nonebot_plugin_web/fastapi.py
nonebot_plugin_web/sender.py
nonebot_plugin_web/webSio.py
nonebot_plugin_web-0.1.4.dist-info/LICENSE
nonebot_plugin_web-0.1.4.dist-info/WHEEL
nonebot_plugin_web-0.1.4.dist-info/METADATA
nonebot_plugin_web-0.1.4.dist-info/RECORD
